shash/__init__.py
shash/dataprep.py
shash/evaluation.py
shash/model_runner.py
shash/modelprep.py
shash-0.2.1.dist-info/LICENSE
shash-0.2.1.dist-info/METADATA
shash-0.2.1.dist-info/WHEEL
shash-0.2.1.dist-info/RECORD
